{
  "swagger": "2.0",
  "info": {
    "title": "profilestore/profilestore.proto",
    "version": "version not set"
  },
  "tags": [
    {
      "name": "ProfileStore"
    }
  ],
  "consumes": [
    "application/json"
  ],
  "produces": [
    "application/json"
  ],
  "paths": {
    "/profiles/writeraw": {
      "post": {
        "operationId": "ProfileStore_WriteRaw",
        "responses": {
          "200": {
            "description": "A successful response.",
            "schema": {
              "$ref": "#/definitions/apiWriteRawResponse"
            }
          },
          "default": {
            "description": "An unexpected error response.",
            "schema": {
              "$ref": "#/definitions/rpcStatus"
            }
          }
        },
        "parameters": [
          {
            "name": "body",
            "in": "body",
            "required": true,
            "schema": {
              "$ref": "#/definitions/apiWriteRawRequest"
            }
          }
        ],
        "tags": [
          "ProfileStore"
        ]
      }
    }
  },
  "definitions": {
    "apiLabelSet": {
      "type": "object",
      "properties": {
        "labels": {
          "type": "array",
          "items": {
            "$ref": "#/definitions/parcaapiLabel"
          }
        }
      }
    },
    "apiRawProfileSeries": {
      "type": "object",
      "properties": {
        "labels": {
          "$ref": "#/definitions/apiLabelSet"
        },
        "samples": {
          "type": "array",
          "items": {
            "$ref": "#/definitions/apiRawSample"
          }
        }
      }
    },
    "apiRawSample": {
      "type": "object",
      "properties": {
        "rawProfile": {
          "type": "string",
          "format": "byte"
        }
      }
    },
    "apiWriteRawRequest": {
      "type": "object",
      "properties": {
        "tenant": {
          "type": "string"
        },
        "series": {
          "type": "array",
          "items": {
            "$ref": "#/definitions/apiRawProfileSeries"
          }
        }
      }
    },
    "apiWriteRawResponse": {
      "type": "object"
    },
    "parcaapiLabel": {
      "type": "object",
      "properties": {
        "name": {
          "type": "string"
        },
        "value": {
          "type": "string"
        }
      }
    },
    "protobufAny": {
      "type": "object",
      "properties": {
        "typeUrl": {
          "type": "string"
        },
        "value": {
          "type": "string",
          "format": "byte"
        }
      }
    },
    "rpcStatus": {
      "type": "object",
      "properties": {
        "code": {
          "type": "integer",
          "format": "int32"
        },
        "message": {
          "type": "string"
        },
        "details": {
          "type": "array",
          "items": {
            "$ref": "#/definitions/protobufAny"
          }
        }
      }
    }
  }
}
